phonetic_manipulation/__init__.py
phonetic_manipulation/phonetic_manipulation.py
phonetic_manipulation/data/diacritic_mappings.csv
phonetic_manipulation/data/phoneset_mapping.csv
phonetic_manipulation-0.0.20.dist-info/LICENSE
phonetic_manipulation-0.0.20.dist-info/METADATA
phonetic_manipulation-0.0.20.dist-info/WHEEL
phonetic_manipulation-0.0.20.dist-info/top_level.txt
phonetic_manipulation-0.0.20.dist-info/RECORD
