Metadata-Version: 2.1
Name: phonetic-manipulation
Version: 0.0.20
Summary: A package for manipulating phonetic transcriptions
Home-page: UNKNOWN
Author: Denny O'Shea
Author-email: denjaminpip@gmail.com
License: UNKNOWN
Keywords: python,phonetics,phonology,computational linguistics,IPA conversion
Platform: UNKNOWN
License-File: LICENSE
Requires-Dist: pandas
